pserialize/__init__.py
pserialize/deserialize.py
pserialize/serialization_utils.py
pserialize/serialize.py
pserializeation-0.0.1.dist-info/LICENSE
pserializeation-0.0.1.dist-info/METADATA
pserializeation-0.0.1.dist-info/WHEEL
pserializeation-0.0.1.dist-info/top_level.txt
pserializeation-0.0.1.dist-info/RECORD
