Metadata-Version: 2.1
Name: pserializeation
Version: 0.0.1
Summary: A de/serialization library for python
Home-page: https://github.com/SteffenCucos/PSerialization
Author: Steffen
Author-email: steffen.cucos@gmail.com
Classifier: Programming Language :: Python :: 3
Classifier: License :: OSI Approved :: MIT License
Classifier: Operating System :: OS Independent
Requires-Python: >=3.9
License-File: LICENSE
